MANIFEST.in
setup.py
bin/starbucks_login.py
starbucks_wifi/__init__.py
starbucks_wifi/login.py
starbucks_wifi/webdriver/chromedriver
starbucks_wifi_login_in_kor.egg-info/PKG-INFO
starbucks_wifi_login_in_kor.egg-info/SOURCES.txt
starbucks_wifi_login_in_kor.egg-info/dependency_links.txt
starbucks_wifi_login_in_kor.egg-info/requires.txt
starbucks_wifi_login_in_kor.egg-info/top_level.txt