Metadata-Version: 1.1
Name: starbucks-wifi-login-in-kor
Version: 1.2
Summary: When you go starbucks in korea, you can be asked your information. This program will input the information based on your data
Home-page: https://github.com/jinniahn/auto_starbuck_wifi_login
Author: jinsub ahn
Author-email: jinniahn@gmail.com
License: BSD
Keywords: starbucks,autologin
Platform: UNKNOWN
Classifier: Development Status :: 3 - Alpha
Classifier: Topic :: Utilities
Classifier: License :: OSI Approved :: BSD License
